{
  "id": 51,
  "name": "ExpandIcon",
  "localName": "펼치기 아이콘",
  "info": "펼치기 버튼으로, 클릭 시 180도 회전 애니메이션을 자동으로 실행합니다. 색상, 크기, 여백을 지정할 수 있으며 클릭 이벤트를 받습니다.",
  "lever": 1,
  "family": 1,
  "linkIds": [
    66,
    125
  ],
  "nodes": [
    {
      "file": "node1_base.dart",
      "name": "ExpandIcon 기본 사용",
      "desc": [
        "【isExpanded】 : 펼쳐져 있는지 여부   【bool】",
        "【padding】 : 안쪽 여백   【EdgeInsetsGeometry】,",
        "【size】 : 아이콘 크기   【double】",
        "【color】 : 펼쳐지지 않았을 때 색상   【Color】",
        "【expandedColor】 : 펼쳐졌을 때 색상   【Color】",
        "【onPressed】 : 클릭 이벤트   【Function(bool)】"
      ]
    }
  ]
}