{"name":"CupertinoPageScaffold","path":"/src/cupertino/page_scaffold.dart","parents":["StatefulWidget","Widget"],"desc":" Implements a single iOS application page's layout.","fields":[{"name":"navigationBar","type":"ObstructingPreferredSizeWidget?","desc":"The [navigationBar], typically a [CupertinoNavigationBar], is drawn at the top of the screen."},{"name":"child","type":"Widget","required":true,"desc":"Widget to show in the main content area."},{"name":"backgroundColor","type":"Color?","desc":"The color of the widget that underlies the entire scaffold."},{"name":"resizeToAvoidBottomInset","type":"bool","required":true,"desc":"Whether the [child] should size itself to avoid the window's bottom inset."}],"id":157,"lever":3,"family":1,"linkIds":[],"nodes":[{"file":"node1_base.dart","name":"Basic Usage of CupertinoPageScaffold","desc":["【child】 : Content   【Widget】","【backgroundColor】 : Background Color   【Color】","【navigationBar】 : Header   【ObstructingPreferredSizeWidget】"]}]}