{"name":"InteractiveViewer","path":"/src/widgets/interactive_viewer.dart","parents":["StatefulWidget","Widget"],"desc":" A widget that enables pan and zoom interactions with its child.","fields":[{"name":"alignment","type":"Alignment?","desc":"The alignment of the child's origin, relative to the size of the box."},{"name":"clipBehavior","type":"Clip","required":true,"desc":"If set to [Clip.none], the child may extend beyond the size of the InteractiveViewer, but it will not receive gestures in these areas. Be sure that the InteractiveViewer is the desired size when using [Clip.none]."},{"name":"panAxis","type":"PanAxis","required":true,"desc":"When set to [PanAxis.aligned], panning is only allowed in the horizontal axis or the vertical axis, diagonal panning is not allowed."},{"name":"boundaryMargin","type":"EdgeInsets","required":true,"desc":"A margin for the visible boundaries of the child."},{"name":"builder","type":"InteractiveViewerWidgetBuilder?","desc":"Builds the child of this widget."},{"name":"child","type":"Widget?","desc":"The child [Widget] that is transformed by InteractiveViewer."},{"name":"constrained","type":"bool","required":true,"desc":"Whether the normal size constraints at this point in the widget tree are applied to the child."},{"name":"panEnabled","type":"bool","required":true,"desc":"If false, the user will be prevented from panning."},{"name":"scaleEnabled","type":"bool","required":true,"desc":"If false, the user will be prevented from scaling."},{"name":"trackpadScrollCausesScale","type":"bool","required":true,"desc":"{@macro flutter.gestures.scale.trackpadScrollCausesScale}"},{"name":"scaleFactor","type":"double","required":true,"desc":"Determines the amount of scale to be performed per pointer scroll."},{"name":"maxScale","type":"double","required":true,"desc":"The maximum allowed scale."},{"name":"minScale","type":"double","required":true,"desc":"The minimum allowed scale."},{"name":"interactionEndFrictionCoefficient","type":"double","required":true,"desc":"Changes the deceleration behavior after a gesture."},{"name":"onInteractionEnd","type":"GestureScaleEndCallback?","desc":"Called when the user ends a pan or scale gesture on the widget."},{"name":"onInteractionStart","type":"GestureScaleStartCallback?","desc":"Called when the user begins a pan or scale gesture on the widget."},{"name":"onInteractionUpdate","type":"GestureScaleUpdateCallback?","desc":"Called when the user updates a pan or scale gesture on the widget."},{"name":"transformationController","type":"TransformationController?","desc":"A [TransformationController] for the transformation performed on the child."}],"id":351,"lever":4,"family":1,"linkIds":[147,146,78],"nodes":[{"file":"node1_base.dart","name":"Basic Usage of InteractiveViewer","desc":["【alignPanAxis】: Drag along the axis 【bool】","【boundaryMargin】: Boundary margin 【EdgeInsets】","【panEnabled】: Whether panning is enabled 【bool】","【scaleEnabled】: Whether scaling is enabled 【bool】","【maxScale】: Maximum zoom scale 【double】","【minScale】: Minimum zoom scale 【double】","【onInteractionEnd】: Interaction end callback 【GestureScaleEndCallback】","【onInteractionStart】: Interaction start callback 【GestureScaleStartCallback】","【onInteractionUpdate】: Interaction update callback 【GestureScaleUpdateCallback】","【child】: Cursor color 【Widget】"]},{"file":"node2_constrained.dart","name":"Constrained Property Test","desc":["【constrained】: Constrained 【bool】"]},{"file":"node3_controller.dart","name":"Usage of Transformation Controller","desc":["【transformationController】: Transformation controller 【TransformationController】"]}]}