{
  "id": 9,
  "name": "CircleAvatar",
  "localName": "Composant Circulaire",
  "info": "Permet de transformer une image en cercle et de placer un composant au centre. Peut spécifier le rayon, la couleur de premier plan, la couleur d'arrière-plan, etc.",
  "lever": 4,
  "family": 0,
  "linkIds": [],
  "nodes": [
    {
      "file": "node1_base.dart",
      "name": "Comportement de CircleAvatar",
      "desc": [
        "【radius】 : rayon  【double】",
        "【backgroundImage】 : ressource d'image  【ImageProvider】",
        "【foregroundColor】: couleur de premier plan   【Color】",
        "【backgroundColor】: couleur d'arrière-plan   【Color】",
        "【minRadius】: rayon minimum   【double】",
        "【maxRadius】: rayon maximum   【double】",
        "【child】: composant enfant   【Child】"
      ]
    }
  ]
}