{
  "id": 352,
  "name": "CupertinoDialogAction",
  "localName": "インタラクティブビュー",
  "info": "シンプルなボタンで、通常はCupertinoAlertDialogで使用され、単独で使用されることはあまりありません。",
  "lever": 1,
  "family": 0,
  "linkIds": [],
  "nodes": [
    {
      "file": "node1_base.dart",
      "name": "CupertinoDialogActionの基本的な使用",
      "desc": [
        "【isDefaultAction】 : デフォルトの操作かどうか   【bool】",
        "【isDestructiveAction】 : 破壊的な操作かどうか   【bool】",
        "【textStyle】: テキストスタイル   【TextStyle】",
        "【onPressed】: クリックイベント   【VoidCallback】",
        "【child】: 子コンポーネント   【Widget】"
      ]
    }
  ]
}