{
  "id": 261,
  "name": "MergeableMaterial",
  "localName": "マージ可能な材料",
  "info": "MergeableMaterialItemのリストを表示するために使用され、MaterialSlice（本体）とMaterialGap（区切り）を含みます。",
  "lever": 1,
  "family": 1,
  "linkIds": [],
  "nodes": [
    {
      "file": "node1_base.dart",
      "name": "MergeableMaterialの基本使用",
      "desc": [
        "【elevation】 : 影の深さ   【double】",
        "【hasDividers】 : 区切り線があるかどうか   【bool】",
        "【dividerColor】 : 区切り線の色   【Color】",
        "【mainAxis】 : 軸方向   【Axis】",
        "【children】 : 子コンポーネントセット   【List<MergeableMaterialItem>】"
      ]
    }
  ]
}