{
  "id": 257,
  "name": "DrawerController",
  "localName": "Onglets glissants iOS",
  "info": "Fournit des comportements interactifs pour le composant Drawer, généralement peu utilisé. Utilisé dans le code source du composant Scaffold.",
  "lever": 3,
  "family": 1,
  "linkIds": [
    154,
    64
  ],
  "nodes": [
    {
      "file": "node1_base.dart",
      "name": "Utilisation de base de DrawerController",
      "desc": [
        "【drawerCallback】 : Rappel d'événement   【DrawerCallback】",
        "【enableOpenDragGesture】 : Glissement latéral activé   【bool】",
        "【alignment】 : Mode d'alignement   【DrawerAlignment】",
        "【scrimColor】 : Couleur de fond   【Color】",
        "【child】 : Composant Drawer   【Widget】"
      ]
    }
  ]
}