{
  "id": 194,
  "name": "Scrollbar",
  "localName": "Barra de desplazamiento",
  "info": "Debe envolver un área desplazable. Cuando es desplazable, se mostrará una barra de desplazamiento para indicar.",
  "lever": 3,
  "family": 1,
  "linkIds": [
    195,
    164,
    162
  ],
  "nodes": [
    {
      "file": "node1_base.dart",
      "name": "Uso básico de Scrollbar",
      "desc": [
        "【child】 : Componente hijo   【Widget】",
        "【controller】 : Controlador  【ScrollController】"
      ]
    }
  ]
}