{"name":"SizedOverflowBox","path":"/src/widgets/basic.dart","parents":["SingleChildRenderObjectWidget","RenderObjectWidget","Widget"],"desc":"具有特定大小但将其原始约束传递给其子项的小部件，然后子项可能会溢出。","fields":[{"name":"alignment","type":"AlignmentGeometry","required":true,"desc":"如何对齐子项。"},{"name":"size","type":"Size","required":true,"desc":"此小部件应尝试达到的大小。"}],"id":84,"localName":"尺寸溢出盒","lever":3,"family":2,"linkIds":[],"nodes":[{"file":"node1_base.dart","name":"SizedOverflowBox基本使用","desc":["【child】 : 孩子组件   【Widget】","【size】 : 尺寸偏移   【Size】","【alignment】 : 对齐方式   【AlignmentGeometry】"]}]}