{
  "id": 146,
  "name": "GestureDetector",
  "localName": "Gesture Detector",
  "info": "A detector for component gesture events, capable of accepting events such as tap, long press, double tap, press, release, move, etc., and can obtain touch information. An essential component for home and travel.",
  "lever": 5,
  "family": 0,
  "linkIds": [
    147,
    150
  ],
  "nodes": [
    {
      "file": "node1_base.dart",
      "name": "Basic Events of GestureDetector",
      "desc": [
        "【child】 : Child component   【Widget】",
        "【onTap】 : Tap event   【Function()】",
        "【onDoubleTap】 : Double tap event   【GestureTapCallback】",
        "【onLongPress】 : Long press event   【GestureLongPressCallback】"
      ]
    },
    {
      "file": "node2_tap.dart",
      "name": "Details of GestureDetector",
      "desc": [
        "【onTapDown】 : Press down callback   【GestureTapDownCallback】",
        "【onTapUp】 : Tap release callback   【GestureTapUpCallback】",
        "【onTapCancel】 : Tap cancel   【GestureTapCancelCallback】"
      ]
    },
    {
      "file": "node3_pan.dart",
      "name": "Pan Events of GestureDetector",
      "desc": [
        "【onPanDown】 : Press down callback   【GestureDragDownCallback】",
        "【onPanEnd】 : Drag end   【GestureDragEndCallback】",
        "【onPanStart】 : Drag start   【GestureDragStartCallback】",
        "【onPanUpdate】 : Drag update   【GestureDragUpdateCallback】",
        "【onPanCancel】 : Drag cancel   【GestureDragCancelCallback】"
      ]
    }
  ]
}