{
  "id": 293,
  "name": "MouseRegion",
  "localName": "Area del Mouse",
  "info": "Componente per il monitoraggio degli eventi del mouse, comunemente utilizzato su piattaforme desktop e web, in grado di monitorare eventi di entrata, uscita e movimento del mouse.",
  "lever": 3,
  "family": 2,
  "linkIds": [],
  "nodes": [
    {
      "file": "node1_base.dart",
      "name": "Uso di base di MouseRegion",
      "desc": [
        "【onEnter】: Evento di entrata   【PointerEnterEventListener】",
        "【onHover】: Evento di movimento    【PointerHoverEventListener】",
        "【onExit】: Evento di uscita    【PointerExitEventListener】"
      ]
    }
  ]
}