{
  "id": 75,
  "name": "Baseline",
  "localName": "Componente de Linha de Base",
  "info": "Pode acomodar um componente filho, controlando a posição do componente filho através da altura da linha de base. Geralmente usado para componentes de texto.",
  "lever": 2,
  "family": 2,
  "linkIds": [],
  "nodes": [
    {
      "file": "node1_base.dart",
      "name": "Uso Básico do Baseline",
      "desc": [
        "【child】 : Componente filho   【Widget】",
        "【baseline】 : Posição da linha de base   【double】",
        "【baselineType】 : Tipo de linha de base   【TextBaseline】"
      ]
    }
  ]
}