{
  "id": 49,
  "name": "RefreshIndicator",
  "localName": "Индикатор обновления",
  "info": "Внутренняя вложенная область с возможностью прокрутки, при прокрутке вниз отображается значок обновления, после отпускания можно выполнить указанный асинхронный метод. Можно указать такие свойства, как цвет, расстояние до верхнего края и т.д.",
  "lever": 4,
  "family": 1,
  "linkIds": [],
  "nodes": [
    {
      "file": "node1_base.dart",
      "name": "Основное использование RefreshIndicator",
      "desc": [
        "【child】 : Дочерний элемент (с возможностью прокрутки)   【Widget】",
        "【displacement】 : Высота индикатора   【double】",
        "【color】 : Цвет индикатора   【Color】"
      ]
    }
  ]
}