{
  "id": 8,
  "name": "FadeInImage",
  "localName": "Imagem de Desvanecimento",
  "info": "Carrega uma imagem com um gradiente transparente. Pode especificar uma imagem de placeholder, curvas de animação de entrada e saída, duração, largura, altura, tipo de ajuste, alinhamento, modo de repetição, etc.",
  "lever": 2,
  "family": 0,
  "linkIds": [],
  "nodes": [
    {
      "file": "node1_base.dart",
      "name": "FadeInImage.assetNetwork carregar imagem da rede",
      "desc": [
        "【placeholder】 : endereço da imagem de placeholder  【String】",
        "【image】 : endereço da imagem a ser exibida  【String】",
        "【width】: largura   【double】",
        "【height】: altura   【double】",
        "【fadeInDuration】: duração do desvanecimento de entrada   【Duration】",
        "【fadeOutDuration】: duração do desvanecimento de saída   【Duration】",
        "【fadeInCurve】: curva de desvanecimento de entrada   【Cubic】",
        "【fadeOutCurve】: curva de desvanecimento de saída   【Cubic】",
        "【fit】: modo de ajuste   【BoxFit】",
        "【alignment】: modo de alinhamento   【Alignment】",
        "【repeat】: modo de repetição   【ImageRepeat】,"
      ]
    }
  ]
}